mcp_server/__init__.py
mcp_server/google_docs_service.py
mcp_server/mcp_server.py
mcp_google_docs-0.2.14.dist-info/METADATA
mcp_google_docs-0.2.14.dist-info/WHEEL
mcp_google_docs-0.2.14.dist-info/entry_points.txt
mcp_google_docs-0.2.14.dist-info/top_level.txt
mcp_google_docs-0.2.14.dist-info/RECORD
