Metadata-Version: 2.2
Name: mcp-google-docs
Version: 0.2.14
Summary: mcp server for viewing, editing, creating, google docs (supports comments)
Requires-Python: >=3.13
Requires-Dist: google-api-python-client>=2.160.0
Requires-Dist: google-auth>=2.38.0
Requires-Dist: google-auth-oauthlib>=1.2.1
Requires-Dist: httplib2>=0.22.0
Requires-Dist: mcp>=1.2.1
Requires-Dist: python-dotenv>=1.0.1
